odoo/addons/fieldservice_repair/README.rst
odoo/addons/fieldservice_repair/__init__.py
odoo/addons/fieldservice_repair/__manifest__.py
odoo/addons/fieldservice_repair/data/fsm_order_type.xml
odoo/addons/fieldservice_repair/i18n/de.po
odoo/addons/fieldservice_repair/i18n/es.po
odoo/addons/fieldservice_repair/i18n/es_AR.po
odoo/addons/fieldservice_repair/i18n/fieldservice_repair.pot
odoo/addons/fieldservice_repair/i18n/fr.po
odoo/addons/fieldservice_repair/i18n/it.po
odoo/addons/fieldservice_repair/i18n/pt_BR.po
odoo/addons/fieldservice_repair/migrations/18.0.2.0.0/post-migrate.py
odoo/addons/fieldservice_repair/models/__init__.py
odoo/addons/fieldservice_repair/models/fsm_order.py
odoo/addons/fieldservice_repair/models/fsm_order_type.py
odoo/addons/fieldservice_repair/models/repair_order.py
odoo/addons/fieldservice_repair/readme/CONFIGURE.md
odoo/addons/fieldservice_repair/readme/CONTRIBUTORS.md
odoo/addons/fieldservice_repair/readme/CREDITS.md
odoo/addons/fieldservice_repair/readme/DESCRIPTION.md
odoo/addons/fieldservice_repair/readme/INSTALL.md
odoo/addons/fieldservice_repair/readme/ROADMAP.md
odoo/addons/fieldservice_repair/readme/USAGE.md
odoo/addons/fieldservice_repair/static/description/icon.png
odoo/addons/fieldservice_repair/static/description/index.html
odoo/addons/fieldservice_repair/tests/__init__.py
odoo/addons/fieldservice_repair/tests/test_fsm_repair.py
odoo/addons/fieldservice_repair/views/fsm_order_view.xml
odoo_addon_fieldservice_repair-18.0.3.0.1.dist-info/METADATA
odoo_addon_fieldservice_repair-18.0.3.0.1.dist-info/WHEEL
odoo_addon_fieldservice_repair-18.0.3.0.1.dist-info/top_level.txt
odoo_addon_fieldservice_repair-18.0.3.0.1.dist-info/RECORD
